bytetype/__init__.py
bytetype/_modidx.py
bytetype/bytes.py
bytetype/enums.py
bytetype/units.py
bytetype/utils.py
bytetype-0.0.6.dist-info/LICENSE
bytetype-0.0.6.dist-info/METADATA
bytetype-0.0.6.dist-info/WHEEL
bytetype-0.0.6.dist-info/entry_points.txt
bytetype-0.0.6.dist-info/top_level.txt
bytetype-0.0.6.dist-info/RECORD
