Metadata-Version: 2.1
Name: bytetype
Version: 0.0.6
Summary: byte type
Home-page: https://github.com/dsm-72/bytetype
Author: dsm-72
Author-email: sumner.magruder@yale.edu
License: Apache Software License 2.0
Keywords: nbdev jupyter notebook python byte bytes kilo tera giga unit dataclass strenum
Classifier: Development Status :: 4 - Beta
Classifier: Intended Audience :: Developers
Classifier: Natural Language :: English
Classifier: Programming Language :: Python :: 3.11
Classifier: License :: OSI Approved :: Apache Software License
Requires-Python: >=3.11
License-File: LICENSE
Requires-Dist: pstr
Provides-Extra: dev
